{
    "dateDeDebut": "03/07/2024",
    "dateDeFin": "03/07/2024",
    "lieu": "CI",
    "nom": "CAN",
    "nombreDeMatchParTour": 4.0,
    "nombreTours": 7,
    "numeroTourActuel": 7,
    "tours": [
        {
            "dateDeDebut": "",
            "dateDeFin": "",
            "matchs": [
                {
                    "scoring1": {
                        "joueur": {
                            "dateDeNaissance": "1111",
                            "id": "AZEER",
                            "nom": "ASAZ",
                            "point": 0,
                            "prenom": "AAIIOEO"
                        },
                        "score": 1
                    },
                    "scoring2": {
                        "joueur": {
                            "dateDeNaissance": "01/01/2000",
                            "id": "IK00004",
                            "nom": "Ballo",
                            "point": 1,
                            "prenom": "Madou"
                        },
                        "score": 2
                    }
                },
                {
                    "scoring1": {
                        "joueur": {
                            "dateDeNaissance": "01/01/2000",
                            "id": "IK00006",
                            "nom": "Diawara",
                            "point": 3.5,
                            "prenom": "Issa"
                        },
                        "score": 1
                    },
                    "scoring2": {
                        "joueur": {
                            "dateDeNaissance": "01/01/1988",
                            "id": "IK00001",
                            "nom": "Diawara",
                            "point": 4,
                            "prenom": "Souley"
                        },
                        "score": 3
                    }
                },
                {
                    "scoring1": {
                        "joueur": {
                            "dateDeNaissance": "111",
                            "id": "AEEDJ",
                            "nom": "ISO",
                            "point": 3.5,
                            "prenom": "ISSSS"
                        },
                        "score": 4
                    },
                    "scoring2": {
                        "joueur": {
                            "dateDeNaissance": "01/01/2000",
                            "id": "IK00003",
                            "nom": "Ouedrago",
                            "point": 5,
                            "prenom": "Anna"
                        },
                        "score": 5
                    }
                },
                {
                    "scoring1": {
                        "joueur": {
                            "dateDeNaissance": "01/01/2000",
                            "id": "IK00005",
                            "nom": "Sacko",
                            "point": 6,
                            "prenom": "Adbou"
                        },
                        "score": 56
                    },
                    "scoring2": {
                        "joueur": {
                            "dateDeNaissance": "01/01/1993",
                            "id": "IK00002",
                            "nom": "Sacko",
                            "point": 5.0,
                            "prenom": "Dipa"
                        },
                        "score": 3
                    }
                }
            ],
            "nomTour": "Tour XX"
        },
        {
            "dateDeDebut": "",
            "dateDeFin": "",
            "matchs": [
                {
                    "scoring1": {
                        "joueur": {
                            "dateDeNaissance": "1111",
                            "id": "AZEER",
                            "nom": "ASAZ",
                            "point": 0,
                            "prenom": "AAIIOEO"
                        },
                        "score": 4
                    },
                    "scoring2": {
                        "joueur": {
                            "dateDeNaissance": "01/01/2000",
                            "id": "IK00006",
                            "nom": "Diawara",
                            "point": 3.5,
                            "prenom": "Issa"
                        },
                        "score": 5
                    }
                },
                {
                    "scoring1": {
                        "joueur": {
                            "dateDeNaissance": "01/01/2000",
                            "id": "IK00004",
                            "nom": "Ballo",
                            "point": 1,
                            "prenom": "Madou"
                        },
                        "score": 4
                    },
                    "scoring2": {
                        "joueur": {
                            "dateDeNaissance": "01/01/1988",
                            "id": "IK00001",
                            "nom": "Diawara",
                            "point": 4,
                            "prenom": "Souley"
                        },
                        "score": 5
                    }
                },
                {
                    "scoring1": {
                        "joueur": {
                            "dateDeNaissance": "111",
                            "id": "AEEDJ",
                            "nom": "ISO",
                            "point": 3.5,
                            "prenom": "ISSSS"
                        },
                        "score": 4
                    },
                    "scoring2": {
                        "joueur": {
                            "dateDeNaissance": "01/01/2000",
                            "id": "IK00005",
                            "nom": "Sacko",
                            "point": 6,
                            "prenom": "Adbou"
                        },
                        "score": 5
                    }
                },
                {
                    "scoring1": {
                        "joueur": {
                            "dateDeNaissance": "01/01/2000",
                            "id": "IK00003",
                            "nom": "Ouedrago",
                            "point": 5,
                            "prenom": "Anna"
                        },
                        "score": 4
                    },
                    "scoring2": {
                        "joueur": {
                            "dateDeNaissance": "01/01/1993",
                            "id": "IK00002",
                            "nom": "Sacko",
                            "point": 5.0,
                            "prenom": "Dipa"
                        },
                        "score": 5
                    }
                }
            ],
            "nomTour": "Tour XX"
        },
        {
            "dateDeDebut": "",
            "dateDeFin": "",
            "matchs": [
                {
                    "scoring1": {
                        "joueur": {
                            "dateDeNaissance": "1111",
                            "id": "AZEER",
                            "nom": "ASAZ",
                            "point": 0,
                            "prenom": "AAIIOEO"
                        },
                        "score": 1
                    },
                    "scoring2": {
                        "joueur": {
                            "dateDeNaissance": "01/01/1988",
                            "id": "IK00001",
                            "nom": "Diawara",
                            "point": 4,
                            "prenom": "Souley"
                        },
                        "score": 3
                    }
                },
                {
                    "scoring1": {
                        "joueur": {
                            "dateDeNaissance": "01/01/2000",
                            "id": "IK00004",
                            "nom": "Ballo",
                            "point": 1,
                            "prenom": "Madou"
                        },
                        "score": 4
                    },
                    "scoring2": {
                        "joueur": {
                            "dateDeNaissance": "01/01/2000",
                            "id": "IK00006",
                            "nom": "Diawara",
                            "point": 3.5,
                            "prenom": "Issa"
                        },
                        "score": 5
                    }
                },
                {
                    "scoring1": {
                        "joueur": {
                            "dateDeNaissance": "111",
                            "id": "AEEDJ",
                            "nom": "ISO",
                            "point": 3.5,
                            "prenom": "ISSSS"
                        },
                        "score": 5
                    },
                    "scoring2": {
                        "joueur": {
                            "dateDeNaissance": "01/01/1993",
                            "id": "IK00002",
                            "nom": "Sacko",
                            "point": 5.0,
                            "prenom": "Dipa"
                        },
                        "score": 5
                    }
                },
                {
                    "scoring1": {
                        "joueur": {
                            "dateDeNaissance": "01/01/2000",
                            "id": "IK00003",
                            "nom": "Ouedrago",
                            "point": 5,
                            "prenom": "Anna"
                        },
                        "score": 4
                    },
                    "scoring2": {
                        "joueur": {
                            "dateDeNaissance": "01/01/2000",
                            "id": "IK00005",
                            "nom": "Sacko",
                            "point": 6,
                            "prenom": "Adbou"
                        },
                        "score": 3
                    }
                }
            ],
            "nomTour": "Tour XX"
        },
        {
            "dateDeDebut": "",
            "dateDeFin": "",
            "matchs": [
                {
                    "scoring1": {
                        "joueur": {
                            "dateDeNaissance": "1111",
                            "id": "AZEER",
                            "nom": "ASAZ",
                            "point": 0,
                            "prenom": "AAIIOEO"
                        },
                        "score": 1
                    },
                    "scoring2": {
                        "joueur": {
                            "dateDeNaissance": "111",
                            "id": "AEEDJ",
                            "nom": "ISO",
                            "point": 3.5,
                            "prenom": "ISSSS"
                        },
                        "score": 3
                    }
                },
                {
                    "scoring1": {
                        "joueur": {
                            "dateDeNaissance": "01/01/2000",
                            "id": "IK00004",
                            "nom": "Ballo",
                            "point": 1,
                            "prenom": "Madou"
                        },
                        "score": 1
                    },
                    "scoring2": {
                        "joueur": {
                            "dateDeNaissance": "01/01/2000",
                            "id": "IK00003",
                            "nom": "Ouedrago",
                            "point": 5,
                            "prenom": "Anna"
                        },
                        "score": 4
                    }
                },
                {
                    "scoring1": {
                        "joueur": {
                            "dateDeNaissance": "01/01/2000",
                            "id": "IK00006",
                            "nom": "Diawara",
                            "point": 3.5,
                            "prenom": "Issa"
                        },
                        "score": 4
                    },
                    "scoring2": {
                        "joueur": {
                            "dateDeNaissance": "01/01/2000",
                            "id": "IK00005",
                            "nom": "Sacko",
                            "point": 6,
                            "prenom": "Adbou"
                        },
                        "score": 5
                    }
                },
                {
                    "scoring1": {
                        "joueur": {
                            "dateDeNaissance": "01/01/1988",
                            "id": "IK00001",
                            "nom": "Diawara",
                            "point": 4,
                            "prenom": "Souley"
                        },
                        "score": 3
                    },
                    "scoring2": {
                        "joueur": {
                            "dateDeNaissance": "01/01/1993",
                            "id": "IK00002",
                            "nom": "Sacko",
                            "point": 5.0,
                            "prenom": "Dipa"
                        },
                        "score": 5
                    }
                }
            ],
            "nomTour": "Tour XX"
        },
        {
            "dateDeDebut": "",
            "dateDeFin": "",
            "matchs": [
                {
                    "scoring1": {
                        "joueur": {
                            "dateDeNaissance": "1111",
                            "id": "AZEER",
                            "nom": "ASAZ",
                            "point": 0,
                            "prenom": "AAIIOEO"
                        },
                        "score": 1
                    },
                    "scoring2": {
                        "joueur": {
                            "dateDeNaissance": "01/01/2000",
                            "id": "IK00003",
                            "nom": "Ouedrago",
                            "point": 5,
                            "prenom": "Anna"
                        },
                        "score": 2
                    }
                },
                {
                    "scoring1": {
                        "joueur": {
                            "dateDeNaissance": "01/01/2000",
                            "id": "IK00004",
                            "nom": "Ballo",
                            "point": 1,
                            "prenom": "Madou"
                        },
                        "score": 3
                    },
                    "scoring2": {
                        "joueur": {
                            "dateDeNaissance": "111",
                            "id": "AEEDJ",
                            "nom": "ISO",
                            "point": 3.5,
                            "prenom": "ISSSS"
                        },
                        "score": 4
                    }
                },
                {
                    "scoring1": {
                        "joueur": {
                            "dateDeNaissance": "01/01/2000",
                            "id": "IK00006",
                            "nom": "Diawara",
                            "point": 3.5,
                            "prenom": "Issa"
                        },
                        "score": 5
                    },
                    "scoring2": {
                        "joueur": {
                            "dateDeNaissance": "01/01/1993",
                            "id": "IK00002",
                            "nom": "Sacko",
                            "point": 5.0,
                            "prenom": "Dipa"
                        },
                        "score": 5
                    }
                },
                {
                    "scoring1": {
                        "joueur": {
                            "dateDeNaissance": "01/01/1988",
                            "id": "IK00001",
                            "nom": "Diawara",
                            "point": 4,
                            "prenom": "Souley"
                        },
                        "score": 3
                    },
                    "scoring2": {
                        "joueur": {
                            "dateDeNaissance": "01/01/2000",
                            "id": "IK00005",
                            "nom": "Sacko",
                            "point": 6,
                            "prenom": "Adbou"
                        },
                        "score": 5
                    }
                }
            ],
            "nomTour": "Tour XX"
        },
        {
            "dateDeDebut": "",
            "dateDeFin": "",
            "matchs": [
                {
                    "scoring1": {
                        "joueur": {
                            "dateDeNaissance": "1111",
                            "id": "AZEER",
                            "nom": "ASAZ",
                            "point": 0,
                            "prenom": "AAIIOEO"
                        },
                        "score": 1
                    },
                    "scoring2": {
                        "joueur": {
                            "dateDeNaissance": "01/01/2000",
                            "id": "IK00005",
                            "nom": "Sacko",
                            "point": 6,
                            "prenom": "Adbou"
                        },
                        "score": 2
                    }
                },
                {
                    "scoring1": {
                        "joueur": {
                            "dateDeNaissance": "01/01/2000",
                            "id": "IK00004",
                            "nom": "Ballo",
                            "point": 1,
                            "prenom": "Madou"
                        },
                        "score": 4
                    },
                    "scoring2": {
                        "joueur": {
                            "dateDeNaissance": "01/01/1993",
                            "id": "IK00002",
                            "nom": "Sacko",
                            "point": 5.0,
                            "prenom": "Dipa"
                        },
                        "score": 5
                    }
                },
                {
                    "scoring1": {
                        "joueur": {
                            "dateDeNaissance": "01/01/2000",
                            "id": "IK00006",
                            "nom": "Diawara",
                            "point": 3.5,
                            "prenom": "Issa"
                        },
                        "score": 5
                    },
                    "scoring2": {
                        "joueur": {
                            "dateDeNaissance": "01/01/2000",
                            "id": "IK00003",
                            "nom": "Ouedrago",
                            "point": 5,
                            "prenom": "Anna"
                        },
                        "score": 3
                    }
                },
                {
                    "scoring1": {
                        "joueur": {
                            "dateDeNaissance": "01/01/1988",
                            "id": "IK00001",
                            "nom": "Diawara",
                            "point": 4,
                            "prenom": "Souley"
                        },
                        "score": 5
                    },
                    "scoring2": {
                        "joueur": {
                            "dateDeNaissance": "111",
                            "id": "AEEDJ",
                            "nom": "ISO",
                            "point": 3.5,
                            "prenom": "ISSSS"
                        },
                        "score": 2
                    }
                }
            ],
            "nomTour": "Tour XX"
        },
        {
            "dateDeDebut": "",
            "dateDeFin": "",
            "matchs": [
                {
                    "scoring1": {
                        "joueur": {
                            "dateDeNaissance": "1111",
                            "id": "AZEER",
                            "nom": "ASAZ",
                            "point": 0,
                            "prenom": "AAIIOEO"
                        },
                        "score": 1
                    },
                    "scoring2": {
                        "joueur": {
                            "dateDeNaissance": "01/01/1993",
                            "id": "IK00002",
                            "nom": "Sacko",
                            "point": 5.0,
                            "prenom": "Dipa"
                        },
                        "score": 3
                    }
                },
                {
                    "scoring1": {
                        "joueur": {
                            "dateDeNaissance": "01/01/2000",
                            "id": "IK00006",
                            "nom": "Diawara",
                            "point": 3.5,
                            "prenom": "Issa"
                        },
                        "score": 4
                    },
                    "scoring2": {
                        "joueur": {
                            "dateDeNaissance": "111",
                            "id": "AEEDJ",
                            "nom": "ISO",
                            "point": 3.5,
                            "prenom": "ISSSS"
                        },
                        "score": 5
                    }
                },
                {
                    "scoring1": {
                        "joueur": {
                            "dateDeNaissance": "01/01/2000",
                            "id": "IK00004",
                            "nom": "Ballo",
                            "point": 1,
                            "prenom": "Madou"
                        },
                        "score": 3
                    },
                    "scoring2": {
                        "joueur": {
                            "dateDeNaissance": "01/01/2000",
                            "id": "IK00005",
                            "nom": "Sacko",
                            "point": 6,
                            "prenom": "Adbou"
                        },
                        "score": 5
                    }
                },
                {
                    "scoring1": {
                        "joueur": {
                            "dateDeNaissance": "01/01/1988",
                            "id": "IK00001",
                            "nom": "Diawara",
                            "point": 4,
                            "prenom": "Souley"
                        },
                        "score": 3
                    },
                    "scoring2": {
                        "joueur": {
                            "dateDeNaissance": "01/01/2000",
                            "id": "IK00003",
                            "nom": "Ouedrago",
                            "point": 5,
                            "prenom": "Anna"
                        },
                        "score": 5
                    }
                }
            ],
            "nomTour": "Tour XX"
        }
    ]
}